cna_advogado/__init__.py
cna_advogado/main.py
cna_advogado-0.1.2.dist-info/entry_points.txt
cna_advogado-0.1.2.dist-info/METADATA
cna_advogado-0.1.2.dist-info/WHEEL
cna_advogado-0.1.2.dist-info/RECORD
