Metadata-Version: 2.1
Name: cna_advogado
Version: 0.1.2
Summary: 
Author: levyvix
Author-email: levy.vix@gmail.com
Requires-Python: >=3.11,<4.0
Classifier: Programming Language :: Python :: 3
Classifier: Programming Language :: Python :: 3.11
Classifier: Programming Language :: Python :: 3.12
Requires-Dist: pytest-playwright (>=0.5.0,<0.6.0)
Requires-Dist: typer (>=0.12.3,<0.13.0)
